{
  "generated_at": "2026-07-21 11:24",
  "nepse": {
    "close": 2726.49,
    "change": 7.25,
    "change_pct": 0.27,
    "date": "2026-07-21"
  },
  "market_status": {
    "is_open": false,
    "as_of": "2026-07-21T14:59:59"
  },
  "sectors": [
    {
      "name": "Banking",
      "symbol": "BANKINGIND",
      "close": 1470.24,
      "change": 1.56,
      "change_pct": 0.11
    },
    {
      "name": "Dev. Bank",
      "symbol": "DEVBANKIND",
      "close": 5755.69,
      "change": -23.17,
      "change_pct": -0.4
    },
    {
      "name": "Finance",
      "symbol": "FINANCEIND",
      "close": 2451.5,
      "change": -17.2,
      "change_pct": -0.7
    },
    {
      "name": "Life Ins.",
      "symbol": "LIFEINSUIND",
      "close": 12354.95,
      "change": -14.71,
      "change_pct": -0.12
    },
    {
      "name": "Non-Life Ins.",
      "symbol": "NONLIFEIND",
      "close": 11075.86,
      "change": -16.18,
      "change_pct": -0.15
    },
    {
      "name": "Hydropower",
      "symbol": "HYDROPOWIND",
      "close": 3800.76,
      "change": -2.13,
      "change_pct": -0.06
    },
    {
      "name": "Microfinance",
      "symbol": "MICROFININD",
      "close": 4712.15,
      "change": -1.17,
      "change_pct": -0.02
    },
    {
      "name": "Trading",
      "symbol": "TRADINGIND",
      "close": 3464.43,
      "change": 97.19,
      "change_pct": 2.89
    },
    {
      "name": "Hotels",
      "symbol": "HOTELIND",
      "close": 7460.09,
      "change": -17.87,
      "change_pct": -0.24
    },
    {
      "name": "Mfg & Proc.",
      "symbol": "MANUFACTUREIND",
      "close": 11025.87,
      "change": 70.47,
      "change_pct": 0.64
    },
    {
      "name": "Mutual Fund",
      "symbol": "MUTUALIND",
      "close": 21.56,
      "change": -0.16,
      "change_pct": -0.74
    },
    {
      "name": "Investment",
      "symbol": "INVIDX",
      "close": 101.1,
      "change": 0.5,
      "change_pct": 0.5
    }
  ],
  "breadth": {
    "increased": 103,
    "decreased": 167,
    "unchanged": 13,
    "date": "2026-07-21"
  }
}